osusat_messaging/__init__.py
osusat_messaging/messages.py
osusat_messaging/packet.py
osusat_messaging-1.0.1.dist-info/licenses/LICENSE
osusat_messaging-1.0.1.dist-info/METADATA
osusat_messaging-1.0.1.dist-info/WHEEL
osusat_messaging-1.0.1.dist-info/top_level.txt
osusat_messaging-1.0.1.dist-info/RECORD
