Metadata-Version: 2.4
Name: osusat-messaging
Version: 1.0.1
Summary: OSUSat messaging library (Python bindings)
Author-email: Ethan Eggert <eggertet@oregonstate.edu>
License: MIT License
Requires-Python: >=3.13
License-File: LICENSE
Dynamic: license-file
